README.rst
setup.py
p4swamp/__init__.py
p4swamp/p4swamp.py
p4swamp.egg-info/PKG-INFO
p4swamp.egg-info/SOURCES.txt
p4swamp.egg-info/dependency_links.txt
p4swamp.egg-info/top_level.txt