Metadata-Version: 1.1
Name: p4swamp
Version: 0.3
Summary: A pure Python wrapper for the Perforce command-line client
Home-page: https://github.com/silverdrake11/p4swamp
Author: Kevin Nasto
Author-email: UNKNOWN
License: MIT
Keywords: p4 perforce marshal minimal pure
Platform: UNKNOWN
Classifier: Programming Language :: Python :: 3
Classifier: Programming Language :: Python :: 2
Classifier: Topic :: Software Development :: Version Control
Classifier: License :: OSI Approved :: MIT License
